{
  "$schema": "https://static.modelcontextprotocol.io/schemas/2025-12-11/server.schema.json",
  "name": "io.github.Br0ski777/email-verification",
  "title": "Email Verification API",
  "description": "Verify emails: syntax, MX records, disposable detection, quality scoring. x402 micropayments.",
  "version": "1.0.0",
  "websiteUrl": "https://github.com/Br0ski777/email-verification-x402",
  "repository": {
    "url": "https://github.com/Br0ski777/email-verification-x402",
    "source": "github"
  },
  "remotes": [
    {
      "type": "sse",
      "url": "https://email-verification-x402-production.up.railway.app/mcp"
    }
  ]
}